{
    "typedefs": [
        {
            "name": "CI_STATE",
            "type": "_CI_STATE",
            "data_type": "TypeDecl"
        }
    ],
    "funcdefs": [
        {
            "name": "LoadIFilter",
            "type": {
                "data_type": "TypeDecl",
                "type": "HRESULT"
            },
            "arguments": [
                {
                    "name": "pwcsPath",
                    "data_type": "TypeDecl",
                    "type": "PCWSTR",
                    "sal": []
                },
                {
                    "data_type": "PtrDecl",
                    "type": {
                        "data_type": "TypeDecl",
                        "type": "IUnknown"
                    },
                    "name": "pUnkOuter",
                    "sal": [
                        "in"
                    ]
                },
                {
                    "data_type": "PtrDecl",
                    "type": {
                        "data_type": "PtrDecl",
                        "type": {
                            "data_type": "TypeDecl",
                            "type": "void"
                        }
                    },
                    "name": "ppIUnk",
                    "sal": [
                        "out"
                    ]
                }
            ],
            "api_locations": [
                "Query.dll",
                "NtQuery.dll"
            ]
        },
        {
            "name": "BindIFilterFromStorage",
            "type": {
                "data_type": "TypeDecl",
                "type": "HRESULT"
            },
            "arguments": [
                {
                    "data_type": "PtrDecl",
                    "type": {
                        "data_type": "TypeDecl",
                        "type": "IStorage"
                    },
                    "name": "pStg",
                    "sal": [
                        "in"
                    ]
                },
                {
                    "data_type": "PtrDecl",
                    "type": {
                        "data_type": "TypeDecl",
                        "type": "IUnknown"
                    },
                    "name": "pUnkOuter",
                    "sal": [
                        "in"
                    ]
                },
                {
                    "data_type": "PtrDecl",
                    "type": {
                        "data_type": "PtrDecl",
                        "type": {
                            "data_type": "TypeDecl",
                            "type": "void"
                        }
                    },
                    "name": "ppIUnk",
                    "sal": [
                        "out"
                    ]
                }
            ],
            "api_locations": [
                "Ntquery.dll"
            ]
        },
        {
            "name": "BindIFilterFromStream",
            "type": {
                "data_type": "TypeDecl",
                "type": "HRESULT"
            },
            "arguments": [
                {
                    "data_type": "PtrDecl",
                    "type": {
                        "data_type": "TypeDecl",
                        "type": "IStream"
                    },
                    "name": "pStm",
                    "sal": [
                        "in"
                    ]
                },
                {
                    "data_type": "PtrDecl",
                    "type": {
                        "data_type": "TypeDecl",
                        "type": "IUnknown"
                    },
                    "name": "pUnkOuter",
                    "sal": [
                        "in"
                    ]
                },
                {
                    "data_type": "PtrDecl",
                    "type": {
                        "data_type": "PtrDecl",
                        "type": {
                            "data_type": "TypeDecl",
                            "type": "void"
                        }
                    },
                    "name": "ppIUnk",
                    "sal": [
                        "out"
                    ]
                }
            ],
            "api_locations": [
                "Ntquery.dll"
            ]
        },
        {
            "name": "SetCatalogState",
            "type": {
                "data_type": "TypeDecl",
                "type": "HRESULT"
            },
            "arguments": [
                {
                    "data_type": "PtrDecl",
                    "type": {
                        "data_type": "TypeDecl",
                        "type": "WCHAR"
                    },
                    "name": "pwcsCat",
                    "sal": []
                },
                {
                    "data_type": "PtrDecl",
                    "type": {
                        "data_type": "TypeDecl",
                        "type": "WCHAR"
                    },
                    "name": "pwcsMachine",
                    "sal": []
                },
                {
                    "name": "dwNewState",
                    "data_type": "TypeDecl",
                    "type": "DWORD",
                    "sal": []
                },
                {
                    "data_type": "PtrDecl",
                    "type": {
                        "data_type": "TypeDecl",
                        "type": "DWORD"
                    },
                    "name": "pdwOldState",
                    "sal": []
                }
            ],
            "api_locations": [
                "Ntquery.dll"
            ]
        }
    ]
}